pyWebpp/__init__.py
pyWebpp/htmlCode.py
pyHtmlpp-1.0.1.dist-info/LICENSE
pyHtmlpp-1.0.1.dist-info/METADATA
pyHtmlpp-1.0.1.dist-info/WHEEL
pyHtmlpp-1.0.1.dist-info/top_level.txt
pyHtmlpp-1.0.1.dist-info/RECORD
